restiny/__about__.py
restiny/__init__.py
restiny/__main__.py
restiny/consts.py
restiny/entities.py
restiny/enums.py
restiny/httpx_auths.py
restiny/utils.py
restiny/assets/__init__.py
restiny/assets/style.tcss
restiny/data/db.py
restiny/data/models.py
restiny/data/repos.py
restiny/data/sql/1_initial.sql
restiny/data/sql/2_add_settings_table.sql
restiny/data/sql/3_add_environments_table.sql
restiny/data/sql/__init__.py
restiny/ui/__init__.py
restiny/ui/app.py
restiny/ui/collections_area.py
restiny/ui/request_area.py
restiny/ui/response_area.py
restiny/ui/top_bar_area.py
restiny/ui/url_area.py
restiny/ui/screens/__init__.py
restiny/ui/screens/environments_screen.py
restiny/ui/screens/postman_collection_import_screen.py
restiny/ui/screens/request_or_folder_screen.py
restiny/ui/screens/settings_screen.py
restiny/widgets/__init__.py
restiny/widgets/collections_tree.py
restiny/widgets/confirm_prompt.py
restiny/widgets/custom_directory_tree.py
restiny/widgets/custom_input.py
restiny/widgets/custom_text_area.py
restiny/widgets/dynamic_fields.py
restiny/widgets/password_input.py
restiny/widgets/path_chooser.py
restiny-0.7.1.dist-info/licenses/LICENSE
restiny-0.7.1.dist-info/METADATA
restiny-0.7.1.dist-info/WHEEL
restiny-0.7.1.dist-info/entry_points.txt
restiny-0.7.1.dist-info/top_level.txt
restiny-0.7.1.dist-info/RECORD
