Metadata-Version: 2.4
Name: restiny
Version: 0.7.1
Summary: A minimalist HTTP client, no bullshit
Author-email: Kalebe Chimanski de Almeida <kalebe.chi.almeida@gmail.com>
License:                                  Apache License
Project-URL: Homepage, https://github.com/Kalebe16/restiny
Project-URL: Repository, https://github.com/Kalebe16/restiny
Project-URL: Issues, https://github.com/Kalebe16/restiny/issues
Project-URL: Documentation, https://github.com/Kalebe16/restiny/blob/main/README.md
Keywords: restiny,tui,http,client,terminal,api,testing,textual,cli,developer-tool
Classifier: Development Status :: 5 - Production/Stable
Classifier: Intended Audience :: Developers
Classifier: License :: OSI Approved :: Apache Software License
Classifier: Environment :: Console
Classifier: Typing :: Typed
Classifier: Programming Language :: Python :: 3
Classifier: Programming Language :: Python :: 3.11
Classifier: Programming Language :: Python :: 3.12
Classifier: Programming Language :: Python :: 3.13
Classifier: Programming Language :: Python :: 3.14
Classifier: Operating System :: POSIX :: Linux
Classifier: Operating System :: MacOS
Classifier: Operating System :: Microsoft :: Windows :: Windows 10
Classifier: Operating System :: Microsoft :: Windows :: Windows 11
Classifier: Topic :: Internet :: WWW/HTTP
Classifier: Topic :: Internet :: WWW/HTTP :: Dynamic Content
Classifier: Natural Language :: English
Requires-Python: >=3.11
License-File: LICENSE
Requires-Dist: textual<6.4,>=6.3
Requires-Dist: textual[syntax]
Requires-Dist: httpx<0.29,>=0.28
Requires-Dist: pyperclip<1.10,>=1.9
Requires-Dist: sqlalchemy<3.0,>=2.0
Requires-Dist: pydantic<2.13,>=2.12
Dynamic: license-file
